pymethyl
