Metadata-Version: 1.0
Name: PyMethyl
Version: 0.1.3
Summary: Tool to determine methylation patterns.
Home-page: https://pypi.python.org/pypi/PyMethyl
Author: Cody Watson and Sandy Weng
Author-email: watsonca@email.wofford.edu
License: LICENSE.txt
Keywords: Methylation patterns
Platform: UNKNOWN
